{
  "kind": "collectionType",
  "collectionName": "doctors",
  "info": {
    "singularName": "doctor",
    "pluralName": "doctors",
    "displayName": "Doctor",
    "description": ""
  },
  "options": {
    "draftAndPublish": true
  },
  "pluginOptions": {},
  "attributes": {
    "Name": {
      "type": "string",
      "required": true
    },
    "Address": {
      "type": "string"
    },
    "Patients": {
      "type": "string",
      "required": false
    },
    "Year_of_Experience": {
      "type": "string",
      "required": false
    },
    "StartTime": {
      "type": "time",
      "default": "07:30:00.000"
    },
    "EndTime": {
      "type": "time",
      "default": "18:00:00.000"
    },
    "About": {
      "type": "richtext"
    },
    "Phone": {
      "type": "string",
      "required": false
    },
    "image": {
      "type": "media",
      "multiple": true,
      "required": false,
      "allowedTypes": [
        "images",
        "files"
      ]
    },
    "Premium": {
      "type": "boolean"
    },
    "categories": {
      "type": "relation",
      "relation": "manyToMany",
      "target": "api::category.category",
      "mappedBy": "doctors"
    },
    "appointments": {
      "type": "relation",
      "relation": "oneToMany",
      "target": "api::appointment.appointment",
      "mappedBy": "doctor"
    }
  }
}
